MANIFEST.in
README.md
setup.py
brick/__init__.py
brick/block.py
brick/element.py
brick/exceptions.py
brick/tag.py
brick/tags.py
brick/text.py
brick/utils.py
brick.egg-info/PKG-INFO
brick.egg-info/SOURCES.txt
brick.egg-info/dependency_links.txt
brick.egg-info/top_level.txt