Metadata-Version: 1.0
Name: brick
Version: 0.0.1
Summary: brick is a pure python templating system.
Home-page: https://github.com/garindra/brick
Author: Garindra Prahandono
Author-email: garindraprahandono@gmail.com
License: UNKNOWN
Platform: UNKNOWN
